pyfsd-0.0.1.2.dev0.dist-info/METADATA
pyfsd-0.0.1.2.dev0.dist-info/WHEEL
pyfsd-0.0.1.2.dev0.dist-info/licenses/LICENSE
pyfsd/__init__.py
pyfsd/_version.py
pyfsd/auth.py
pyfsd/db_tables.py
pyfsd/define/__init__.py
pyfsd/define/broadcast.py
pyfsd/define/config_check.py
pyfsd/define/errors.py
pyfsd/define/packet.py
pyfsd/define/simulation.py
pyfsd/define/utils.py
pyfsd/factory/__init__.py
pyfsd/factory/client.py
pyfsd/metar/__init__.py
pyfsd/metar/fetch.py
pyfsd/metar/manager.py
pyfsd/metar/profile.py
pyfsd/metar/service.py
pyfsd/object/__init__.py
pyfsd/object/client.py
pyfsd/plugin.py
pyfsd/plugins/__init__.py
pyfsd/prompt/__init__.py
pyfsd/prompt/protocol.py
pyfsd/prompt/raw_mode.py
pyfsd/prompt/raw_mode.pyi
pyfsd/prompt/service.py
pyfsd/prompt/stdout_helper.py
pyfsd/prompt/utf_8.py
pyfsd/protocol/__init__.py
pyfsd/protocol/client.py
pyfsd/py.typed
pyfsd/service.py
pyfsd/setup_loguru.py
pyfsd/utils/__init__.py
pyfsd/utils/import_users/__init__.py
pyfsd/utils/import_users/__main__.py
pyfsd/utils/import_users/formats.py
twisted/plugins/pyfsd_launcher.py
pyfsd-0.0.1.2.dev0.dist-info/RECORD
